{
  "predicates": [
    {
      "name": "located_at",
      "args": [
        "entity",
        "location"
      ],
      "description": "An entity is located at a specific location"
    },
    {
      "name": "part_of",
      "args": [
        "whole",
        "part"
      ],
      "description": "A part is part of a whole entity"
    },
    {
      "name": "has_author",
      "args": [
        "work",
        "author"
      ],
      "description": "A work has an author"
    },
    {
      "name": "is_married_to",
      "args": [
        "person1",
        "person2"
      ],
      "description": "Two people are married to each other"
    },
    {
      "name": "plays_role_in",
      "args": [
        "entity",
        "role"
      ],
      "description": "An entity plays a specific role in something"
    },
    {
      "name": "has_type",
      "args": [
        "thing",
        "type"
      ],
      "description": "A thing has a specific type or category"
    }
  ]
}